rclonestorage/__init__.py
rclonestorage/rclone.py
rclonestorage/rclone_remote.py
django_rclone_storage-0.1.1.dist-info/LICENSE
django_rclone_storage-0.1.1.dist-info/METADATA
django_rclone_storage-0.1.1.dist-info/WHEEL
django_rclone_storage-0.1.1.dist-info/top_level.txt
django_rclone_storage-0.1.1.dist-info/RECORD
